mongoops/__init__.py
mongoops/ops.py
mongoops-1.0.6.dist-info/LICENSE
mongoops-1.0.6.dist-info/METADATA
mongoops-1.0.6.dist-info/WHEEL
mongoops-1.0.6.dist-info/top_level.txt
mongoops-1.0.6.dist-info/RECORD
